seqann/__init__.py
seqann/align.py
seqann/blast_cmd.py
seqann/gfe.py
seqann/seq_search.py
seqann/sequence_annotation.py
seqann/util.py
seqann/data/feature_lengths.csv
seqann/data/gc_content.csv
seqann/data/kir-feature_lengths.csv
seqann/data/molecular_weight.csv
seqann/data/alignments/3290/A_gen.pickle
seqann/data/alignments/3290/B_gen.pickle
seqann/data/alignments/3290/C_gen.pickle
seqann/data/alignments/3290/DPA1_gen.pickle
seqann/data/alignments/3290/DPB1_gen.pickle
seqann/data/alignments/3290/DQA1_gen.pickle
seqann/data/alignments/3290/DQB1_gen.pickle
seqann/data/alignments/3290/DRB1_gen.pickle
seqann/data/alignments/3300/A_gen.pickle
seqann/data/alignments/3300/B_gen.pickle
seqann/data/alignments/3300/C_gen.pickle
seqann/data/alignments/3300/DPA1_gen.pickle
seqann/data/alignments/3300/DPB1_gen.pickle
seqann/data/alignments/3300/DQA1_gen.pickle
seqann/data/alignments/3300/DQB1_gen.pickle
seqann/data/alignments/3300/DRB1_gen.pickle
seqann/data/alignments/3310/A_gen.pickle
seqann/data/alignments/3310/B_gen.pickle
seqann/data/alignments/3310/C_gen.pickle
seqann/data/alignments/3310/DPA1_gen.pickle
seqann/data/alignments/3310/DPB1_gen.pickle
seqann/data/alignments/3310/DQA1_gen.pickle
seqann/data/alignments/3310/DQB1_gen.pickle
seqann/data/alignments/3310/DRB1_gen.pickle
seqann/data/allele_lists/Allelelist.300.txt
seqann/data/allele_lists/Allelelist.310.txt
seqann/data/allele_lists/Allelelist.3100.txt
seqann/data/allele_lists/Allelelist.3110.txt
seqann/data/allele_lists/Allelelist.3120.txt
seqann/data/allele_lists/Allelelist.3131.txt
seqann/data/allele_lists/Allelelist.3140.txt
seqann/data/allele_lists/Allelelist.3150.txt
seqann/data/allele_lists/Allelelist.3160.txt
seqann/data/allele_lists/Allelelist.3170.txt
seqann/data/allele_lists/Allelelist.3180.txt
seqann/data/allele_lists/Allelelist.3190.txt
seqann/data/allele_lists/Allelelist.320.txt
seqann/data/allele_lists/Allelelist.3200.txt
seqann-1.0.0.dist-info/DESCRIPTION.rst
seqann-1.0.0.dist-info/METADATA
seqann-1.0.0.dist-info/RECORD
seqann-1.0.0.dist-info/WHEEL
seqann-1.0.0.dist-info/metadata.json
seqann-1.0.0.dist-info/top_level.txt
