Metadata-Version: 2.0
Name: seqann
Version: 1.0.0
Summary: Sequence Annotation
Home-page: https://github.com/nmdp-bioinformatics/SeqAnn
Author: Mike Halagan
Author-email: mhalagan@nmdp.org
License: LGPL 3.0
Keywords: seqann
Platform: UNKNOWN
Classifier: Development Status :: 2 - Pre-Alpha
Classifier: Intended Audience :: Developers
Classifier: License :: OSI Approved :: GNU Lesser General Public License v3 (LGPLv3)
Classifier: Natural Language :: English
Classifier: Programming Language :: Python :: 3.6
Requires-Dist: biopython
Requires-Dist: PyMySQL
Requires-Dist: six
Requires-Dist: bson
Requires-Dist: pytz
Requires-Dist: numpy
Requires-Dist: requests
